Hardware/decoder_7seg.v
//For Common Anode (For Common Cathode everything would be complimented)
module decoder_7seg(
    input [3:0] bcd_in,
    output reg [6:0] segments_out
  );

  always @(*) begin
    case (bcd_in)
      //           abcdefg
      4'd0: segments_out = 7'b0000001; // 0
      4'd1: segments_out = 7'b1001111; // 1
      4'd2: segments_out = 7'b0010010; // 2
      4'd3: segments_out = 7'b0000110; // 3
      4'd4: segments_out = 7'b1001100; // 4
      4'd5: segments_out = 7'b0100100; // 5
      4'd6: segments_out = 7'b0100000; // 6
      4'd7: segments_out = 7'b0001111; // 7
      4'd8: segments_out = 7'b0000000; // 8
      4'd9: segments_out = 7'b0000100; // 9
      4'd10: segments_out = 7'b0001000; // A
      4'd11: segments_out = 7'b1100000; // b
      4'd12: segments_out = 7'b0110001; // C
      4'd13: segments_out = 7'b1000010; // d
      4'd14: segments_out = 7'b0110000; // E
      4'd15: segments_out = 7'b0111000; // F
      default: segments_out = 7'b1111111; // Off
    endcase
  end

endmodule

Hardware/debugger.v

module debugger(
    input clk_1hz,          
    input reset,            
    input mode_switch_raw, 
    input step_button_raw,  
    output reg fsm_clk_enable 
);

    wire button_pressed;
    assign button_pressed = ~step_button_raw; 

    // Edge Detector
    // This turns a long press into a single 1-cycle pulse.
    
    reg button_pressed_prev; 
    wire single_pulse;

    always @(posedge clk_1hz or negedge reset) begin
        if (reset == 1'b0) 
            button_pressed_prev <= 1'b0;
        else
            button_pressed_prev <= button_pressed;
    end
    
    //Edge Detection
    assign single_pulse = button_pressed & ~button_pressed_prev;

    //Decides whether in Run Mode or Step Mode
    always @(*) begin
        //In Run Mode
        if (mode_switch_raw == 1'b1) 
            fsm_clk_enable = 1'b1;     
        else // In Step Mode
            fsm_clk_enable = single_pulse; 
    end

endmodule

fsm_core.v

module fsm_core(
    input clk,
    input clk_enable,
    input reset, 
    input [1:0] x_in,
    output [3:0] z_out, 
    output [3:0] current_state_debug
  );

  // State Definitions 
  parameter S0 = 4'd0;
  parameter S1 = 4'd1;
  parameter S2 = 4'd2;
  parameter S3 = 4'd3;
  parameter S4 = 4'd4;
  parameter S5 = 4'd5;
  parameter S6 = 4'd6;
  parameter S7 = 4'd7;
  parameter S8 = 4'd8;
  parameter S9 = 4'd9;
  parameter S10 = 4'd10;
  parameter S11 = 4'd11;
  parameter S12 = 4'd12;
  parameter S13 = 4'd13;
  parameter S14 = 4'd14;
  parameter S15 = 4'd15;

  // State Registers
  reg [3:0] present_state;
  reg [3:0] next_state;
  reg [3:0] z; 

  // State Updation when clock available(the clock signal[clk_enable] will be controlled by debugger)
  always @(posedge clk or negedge reset) begin
    if (reset == 1'b0) 
      present_state <= S0;
    else if (clk_enable) 
      present_state <= next_state;
  end
  
  // The whole FSM in form of case blocks and if-else
  always @(*) begin
    // Safe Defaults
    next_state = S0;
    z = 4'b0000; 

    case (present_state)
        
        //PYTHON-GEN-START
		S0: begin
			case (x_in)
				2'b00: begin next_state = S0; z = 4'b0000; end
				2'b01: begin next_state = S0; z = 4'b0000; end
				2'b10: begin next_state = S1; z = 4'b0000; end
				2'b11: begin next_state = S2; z = 4'b0000; end
				default: begin next_state = S0; z = 4'b0000; end
			endcase
		end

		S1: begin
			case (x_in)
				2'b00: begin next_state = S1; z = 4'b0000; end
				2'b01: begin next_state = S1; z = 4'b0000; end
				2'b10: begin next_state = S2; z = 4'b0000; end
				2'b11: begin next_state = S3; z = 4'b0000; end
				default: begin next_state = S0; z = 4'b0000; end
			endcase
		end

		S2: begin
			case (x_in)
				2'b00: begin next_state = S2; z = 4'b0000; end
				2'b01: begin next_state = S2; z = 4'b0000; end
				2'b10: begin next_state = S3; z = 4'b0000; end
				2'b11: begin next_state = S4; z = 4'b0000; end
				default: begin next_state = S0; z = 4'b0000; end
			endcase
		end

		S3: begin
			case (x_in)
				2'b00: begin next_state = S0; z = 4'b0001; end
				2'b01: begin next_state = S0; z = 4'b0001; end
				2'b10: begin next_state = S0; z = 4'b0001; end
				2'b11: begin next_state = S0; z = 4'b0001; end
				default: begin next_state = S0; z = 4'b0000; end
			endcase
		end

		S4: begin
			case (x_in)
				2'b00: begin next_state = S0; z = 4'b0011; end
				2'b01: begin next_state = S0; z = 4'b0011; end
				2'b10: begin next_state = S0; z = 4'b0011; end
				2'b11: begin next_state = S0; z = 4'b0011; end
				default: begin next_state = S0; z = 4'b0000; end
			endcase
		end

        //PYTHON-GEN-END

        
        // To prevent lock out for unused states
        default: begin 
            next_state = S0;
            z = 4'b0000; 
        end
    endcase
  end
  
  assign current_state_debug = present_state;
  assign z_out = z;

endmodule

Hardware/top_level.v

module top_level(
    // Physical Pin Declarations
    // Inputs (from Helium Board)
    input clk_1hz,          // Pin 43: Onboard 1Hz Clock
    input reset_button,     // Pin 6 (SW3): Global Asynchronous Reset
    input mode_switch,      // Pin 4 (SW1): Run=0, Step=1
    input [1:0] fsm_input_x,  // Pin 5 (SW2), Pin 8 (SW4)
    input step_button,      // Pin 14 (SW8): Single-Step button
    
    // Outputs (to Helium Board & Breadboard)
    output [6:0] segments_out, // Pins 16,18,19,34,37,39,40 (To 7-Seg)
    output [3:0] fsm_output_z  // Pin 33 (LED8), Pin 31 (LED7)
  );

  // Internal Wires
  
  wire fsm_enable_wire;  
  wire [3:0] state_wire; 

  // FSM Core 
  fsm_core FSM_INSTANCE (
    .clk(clk_1hz),
    .clk_enable(fsm_enable_wire), // <-- connected to debugger's output
    .reset(reset_button),
    .x_in(fsm_input_x),         
    .z_out(fsm_output_z),       // --> connected to physical LEDs
    .current_state_debug(state_wire) // --> connected to decoder's input
  );

  // Debugger
  debugger DEBUGGER_INSTANCE (
    .clk_1hz(clk_1hz),
    .reset(reset_button),
    .mode_switch_raw(mode_switch),
    .step_button_raw(step_button),
    .fsm_clk_enable(fsm_enable_wire) // <-- connected to FSM's input
  );
  
  // 7-Segment Decoder
  decoder_7seg DECODER_INSTANCE (
    .bcd_in(state_wire),      // <-- connected to FSM's debug output
    .segments_out(segments_out) // --> connected to 7 Seg output
  );

endmodule

Simulation/tb_top_level.v
`timescale 1ns / 1ps

module tb_counter_fsm;

    // 1. Inputs
    reg clk_1hz;
    reg reset_button_raw;
    reg mode_switch_raw;
    reg [1:0] fsm_input_x_raw; 
    reg step_button_raw;

    // 2. Outputs
    wire [3:0] fsm_output_z;
    wire [6:0] segments_out;

    top_level DUT (
        .clk_1hz(clk_1hz),
        .reset_button(reset_button_raw),
        .mode_switch(mode_switch_raw),
        .fsm_input_x(fsm_input_x_raw),
        .step_button(step_button_raw),
        .fsm_output_z(fsm_output_z),
        .segments_out(segments_out)
    );

    always begin
        #5 clk_1hz = ~clk_1hz;
    end
    
    //  The Test Script
    initial begin
        $dumpfile("waveform.vcd");
        $dumpvars(0, tb_counter_fsm);
        
        
        clk_1hz = 0;
        reset_button_raw = 1'b1;
        mode_switch_raw  = 1'b1; 
        fsm_input_x_raw  = 2'b00; 
        step_button_raw  = 1'b1;
        
        $display("--- Counter FSM Test Start ---");
        
        //Test 1
        $display("T= %0t: Resetting System...", $time);
        reset_button_raw = 1'b0; 
        #100;
        reset_button_raw = 1'b1; 
        #100;

        //Test 2
        $display("T= %0t: Testing Count UP (Input 01)...", $time);
        fsm_input_x_raw = 2'b01; 
        #400; 
        
        //Test 3
        $display("T= %0t: Testing HOLD (Input 00)...", $time);
        fsm_input_x_raw = 2'b00;
        #200; 

        // Test 4
        $display("T= %0t: Testing Count DOWN (Input 10)...", $time);
        fsm_input_x_raw = 2'b10;
        #400; 

        // Test 5
        $display("T= %0t: Testing Soft Reset (Input 11)...", $time);
        fsm_input_x_raw = 2'b11;
        #100; 
        
        $display("--- Test Finished ---");
        $stop;
    end
    
endmodule

Docs/waveform.vcd
$date
	Tue Nov 18 17:01:01 2025
$end
$version
	Icarus Verilog
$end
$timescale
	1ps
$end
$scope module tb_counter_fsm $end
$var wire 7 ! segments_out [6:0] $end
$var wire 4 " fsm_output_z [3:0] $end
$var reg 1 # clk_1hz $end
$var reg 2 $ fsm_input_x_raw [1:0] $end
$var reg 1 % mode_switch_raw $end
$var reg 1 & reset_button_raw $end
$var reg 1 ' step_button_raw $end
$scope module DUT $end
$var wire 1 # clk_1hz $end
$var wire 2 ( fsm_input_x [1:0] $end
$var wire 1 % mode_switch $end
$var wire 1 & reset_button $end
$var wire 1 ' step_button $end
$var wire 4 ) state_wire [3:0] $end
$var wire 7 * segments_out [6:0] $end
$var wire 4 + fsm_output_z [3:0] $end
$var wire 1 , fsm_enable_wire $end
$scope module DEBUGGER_INSTANCE $end
$var wire 1 - button_pressed $end
$var wire 1 # clk_1hz $end
$var wire 1 % mode_switch_raw $end
$var wire 1 & reset $end
$var wire 1 . single_pulse $end
$var wire 1 ' step_button_raw $end
$var reg 1 / button_pressed_prev $end
$var reg 1 , fsm_clk_enable $end
$upscope $end
$scope module DECODER_INSTANCE $end
$var wire 4 0 bcd_in [3:0] $end
$var reg 7 1 segments_out [6:0] $end
$upscope $end
$scope module FSM_INSTANCE $end
$var wire 1 # clk $end
$var wire 1 , clk_enable $end
$var wire 4 2 current_state_debug [3:0] $end
$var wire 1 & reset $end
$var wire 2 3 x_in [1:0] $end
$var wire 4 4 z_out [3:0] $end
$var parameter 4 5 S0 $end
$var parameter 4 6 S1 $end
$var parameter 4 7 S10 $end
$var parameter 4 8 S11 $end
$var parameter 4 9 S12 $end
$var parameter 4 : S13 $end
$var parameter 4 ; S14 $end
$var parameter 4 < S15 $end
$var parameter 4 = S2 $end
$var parameter 4 > S3 $end
$var parameter 4 ? S4 $end
$var parameter 4 @ S5 $end
$var parameter 4 A S6 $end
$var parameter 4 B S7 $end
$var parameter 4 C S8 $end
$var parameter 4 D S9 $end
$var reg 4 E next_state [3:0] $end
$var reg 4 F present_state [3:0] $end
$var reg 4 G z [3:0] $end
$upscope $end
$upscope $end
$upscope $end
$enddefinitions $end
$comment Show the parameter values. $end
$dumpall
b1001 D
b1000 C
b111 B
b110 A
b101 @
b100 ?
b11 >
b10 =
b1111 <
b1110 ;
b1101 :
b1100 9
b1011 8
b1010 7
b1 6
b0 5
$end
#0
$dumpvars
b0 G
b0 F
b0 E
b0 4
b0 3
b0 2
b1 1
b0 0
0/
0.
0-
1,
b0 +
b1 *
b0 )
b0 (
1'
0&
1%
b0 $
0#
b0 "
b1 !
$end
#5000
1#
#10000
0#
#15000
1#
#20000
0#
#25000
1#
#30000
0#
#35000
1#
#40000
0#
#45000
1#
#50000
0#
#55000
1#
#60000
0#
#65000
1#
#70000
0#
#75000
1#
#80000
0#
#85000
1#
#90000
0#
#95000
1#
#100000
0#
1&
#105000
1#
#110000
0#
#115000
1#
#120000
0#
#125000
1#
#130000
0#
#135000
1#
#140000
0#
#145000
1#
#150000
0#
#155000
1#
#160000
0#
#165000
1#
#170000
0#
#175000
1#
#180000
0#
#185000
1#
#190000
0#
#195000
1#
#200000
b1 E
0#
b1 $
b1 (
b1 3
#205000
b1 "
b1 +
b1 4
b1 G
b10 E
b1001111 !
b1001111 *
b1001111 1
b1 )
b1 0
b1 2
b1 F
1#
#210000
0#
#215000
b10 "
b10 +
b10 4
b10 G
b11 E
b10010 !
b10010 *
b10010 1
b10 )
b10 0
b10 2
b10 F
1#
#220000
0#
#225000
b11 "
b11 +
b11 4
b11 G
b0 E
b110 !
b110 *
b110 1
b11 )
b11 0
b11 2
b11 F
1#
#230000
0#
#235000
b1 E
b0 "
b0 +
b0 4
b0 G
b1 !
b1 *
b1 1
b0 )
b0 0
b0 2
b0 F
1#
#240000
0#
#245000
b1 "
b1 +
b1 4
b1 G
b10 E
b1001111 !
b1001111 *
b1001111 1
b1 )
b1 0
b1 2
b1 F
1#
#250000
0#
#255000
b10 "
b10 +
b10 4
b10 G
b11 E
b10010 !
b10010 *
b10010 1
b10 )
b10 0
b10 2
b10 F
1#
#260000
0#
#265000
b11 "
b11 +
b11 4
b11 G
b0 E
b110 !
b110 *
b110 1
b11 )
b11 0
b11 2
b11 F
1#
#270000
0#
#275000
b1 E
b0 "
b0 +
b0 4
b0 G
b1 !
b1 *
b1 1
b0 )
b0 0
b0 2
b0 F
1#
#280000
0#
#285000
b1 "
b1 +
b1 4
b1 G
b10 E
b1001111 !
b1001111 *
b1001111 1
b1 )
b1 0
b1 2
b1 F
1#
#290000
0#
#295000
b10 "
b10 +
b10 4
b10 G
b11 E
b10010 !
b10010 *
b10010 1
b10 )
b10 0
b10 2
b10 F
1#
#300000
0#
#305000
b11 "
b11 +
b11 4
b11 G
b0 E
b110 !
b110 *
b110 1
b11 )
b11 0
b11 2
b11 F
1#
#310000
0#
#315000
b1 E
b0 "
b0 +
b0 4
b0 G
b1 !
b1 *
b1 1
b0 )
b0 0
b0 2
b0 F
1#
#320000
0#
#325000
b1 "
b1 +
b1 4
b1 G
b10 E
b1001111 !
b1001111 *
b1001111 1
b1 )
b1 0
b1 2
b1 F
1#
#330000
0#
#335000
b10 "
b10 +
b10 4
b10 G
b11 E
b10010 !
b10010 *
b10010 1
b10 )
b10 0
b10 2
b10 F
1#
#340000
0#
#345000
b11 "
b11 +
b11 4
b11 G
b0 E
b110 !
b110 *
b110 1
b11 )
b11 0
b11 2
b11 F
1#
#350000
0#
#355000
b1 E
b0 "
b0 +
b0 4
b0 G
b1 !
b1 *
b1 1
b0 )
b0 0
b0 2
b0 F
1#
#360000
0#
#365000
b1 "
b1 +
b1 4
b1 G
b10 E
b1001111 !
b1001111 *
b1001111 1
b1 )
b1 0
b1 2
b1 F
1#
#370000
0#
#375000
b10 "
b10 +
b10 4
b10 G
b11 E
b10010 !
b10010 *
b10010 1
b10 )
b10 0
b10 2
b10 F
1#
#380000
0#
#385000
b11 "
b11 +
b11 4
b11 G
b0 E
b110 !
b110 *
b110 1
b11 )
b11 0
b11 2
b11 F
1#
#390000
0#
#395000
b1 E
b0 "
b0 +
b0 4
b0 G
b1 !
b1 *
b1 1
b0 )
b0 0
b0 2
b0 F
1#
#400000
0#
#405000
b1 "
b1 +
b1 4
b1 G
b10 E
b1001111 !
b1001111 *
b1001111 1
b1 )
b1 0
b1 2
b1 F
1#
#410000
0#
#415000
b10 "
b10 +
b10 4
b10 G
b11 E
b10010 !
b10010 *
b10010 1
b10 )
b10 0
b10 2
b10 F
1#
#420000
0#
#425000
b11 "
b11 +
b11 4
b11 G
b0 E
b110 !
b110 *
b110 1
b11 )
b11 0
b11 2
b11 F
1#
#430000
0#
#435000
b1 E
b0 "
b0 +
b0 4
b0 G
b1 !
b1 *
b1 1
b0 )
b0 0
b0 2
b0 F
1#
#440000
0#
#445000
b1 "
b1 +
b1 4
b1 G
b10 E
b1001111 !
b1001111 *
b1001111 1
b1 )
b1 0
b1 2
b1 F
1#
#450000
0#
#455000
b10 "
b10 +
b10 4
b10 G
b11 E
b10010 !
b10010 *
b10010 1
b10 )
b10 0
b10 2
b10 F
1#
#460000
0#
#465000
b11 "
b11 +
b11 4
b11 G
b0 E
b110 !
b110 *
b110 1
b11 )
b11 0
b11 2
b11 F
1#
#470000
0#
#475000
b1 E
b0 "
b0 +
b0 4
b0 G
b1 !
b1 *
b1 1
b0 )
b0 0
b0 2
b0 F
1#
#480000
0#
#485000
b1 "
b1 +
b1 4
b1 G
b10 E
b1001111 !
b1001111 *
b1001111 1
b1 )
b1 0
b1 2
b1 F
1#
#490000
0#
#495000
b10 "
b10 +
b10 4
b10 G
b11 E
b10010 !
b10010 *
b10010 1
b10 )
b10 0
b10 2
b10 F
1#
#500000
0#
#505000
b11 "
b11 +
b11 4
b11 G
b0 E
b110 !
b110 *
b110 1
b11 )
b11 0
b11 2
b11 F
1#
#510000
0#
#515000
b1 E
b0 "
b0 +
b0 4
b0 G
b1 !
b1 *
b1 1
b0 )
b0 0
b0 2
b0 F
1#
#520000
0#
#525000
b1 "
b1 +
b1 4
b1 G
b10 E
b1001111 !
b1001111 *
b1001111 1
b1 )
b1 0
b1 2
b1 F
1#
#530000
0#
#535000
b10 "
b10 +
b10 4
b10 G
b11 E
b10010 !
b10010 *
b10010 1
b10 )
b10 0
b10 2
b10 F
1#
#540000
0#
#545000
b11 "
b11 +
b11 4
b11 G
b0 E
b110 !
b110 *
b110 1
b11 )
b11 0
b11 2
b11 F
1#
#550000
0#
#555000
b1 E
b0 "
b0 +
b0 4
b0 G
b1 !
b1 *
b1 1
b0 )
b0 0
b0 2
b0 F
1#
#560000
0#
#565000
b1 "
b1 +
b1 4
b1 G
b10 E
b1001111 !
b1001111 *
b1001111 1
b1 )
b1 0
b1 2
b1 F
1#
#570000
0#
#575000
b10 "
b10 +
b10 4
b10 G
b11 E
b10010 !
b10010 *
b10010 1
b10 )
b10 0
b10 2
b10 F
1#
#580000
0#
#585000
b11 "
b11 +
b11 4
b11 G
b0 E
b110 !
b110 *
b110 1
b11 )
b11 0
b11 2
b11 F
1#
#590000
0#
#595000
b1 E
b0 "
b0 +
b0 4
b0 G
b1 !
b1 *
b1 1
b0 )
b0 0
b0 2
b0 F
1#
#600000
b0 E
0#
b0 $
b0 (
b0 3
#605000
1#
#610000
0#
#615000
1#
#620000
0#
#625000
1#
#630000
0#
#635000
1#
#640000
0#
#645000
1#
#650000
0#
#655000
1#
#660000
0#
#665000
1#
#670000
0#
#675000
1#
#680000
0#
#685000
1#
#690000
0#
#695000
1#
#700000
0#
#705000
1#
#710000
0#
#715000
1#
#720000
0#
#725000
1#
#730000
0#
#735000
1#
#740000
0#
#745000
1#
#750000
0#
#755000
1#
#760000
0#
#765000
1#
#770000
0#
#775000
1#
#780000
0#
#785000
1#
#790000
0#
#795000
1#
#800000
b11 E
0#
b10 $
b10 (
b10 3
#805000
b11 "
b11 +
b11 4
b11 G
b10 E
b110 !
b110 *
b110 1
b11 )
b11 0
b11 2
b11 F
1#
#810000
0#
#815000
b10 "
b10 +
b10 4
b10 G
b1 E
b10010 !
b10010 *
b10010 1
b10 )
b10 0
b10 2
b10 F
1#
#820000
0#
#825000
b1 "
b1 +
b1 4
b1 G
b0 E
b1001111 !
b1001111 *
b1001111 1
b1 )
b1 0
b1 2
b1 F
1#
#830000
0#
#835000
b11 E
b0 "
b0 +
b0 4
b0 G
b1 !
b1 *
b1 1
b0 )
b0 0
b0 2
b0 F
1#
#840000
0#
#845000
b11 "
b11 +
b11 4
b11 G
b10 E
b110 !
b110 *
b110 1
b11 )
b11 0
b11 2
b11 F
1#
#850000
0#
#855000
b10 "
b10 +
b10 4
b10 G
b1 E
b10010 !
b10010 *
b10010 1
b10 )
b10 0
b10 2
b10 F
1#
#860000
0#
#865000
b1 "
b1 +
b1 4
b1 G
b0 E
b1001111 !
b1001111 *
b1001111 1
b1 )
b1 0
b1 2
b1 F
1#
#870000
0#
#875000
b11 E
b0 "
b0 +
b0 4
b0 G
b1 !
b1 *
b1 1
b0 )
b0 0
b0 2
b0 F
1#
#880000
0#
#885000
b11 "
b11 +
b11 4
b11 G
b10 E
b110 !
b110 *
b110 1
b11 )
b11 0
b11 2
b11 F
1#
#890000
0#
#895000
b10 "
b10 +
b10 4
b10 G
b1 E
b10010 !
b10010 *
b10010 1
b10 )
b10 0
b10 2
b10 F
1#
#900000
0#
#905000
b1 "
b1 +
b1 4
b1 G
b0 E
b1001111 !
b1001111 *
b1001111 1
b1 )
b1 0
b1 2
b1 F
1#
#910000
0#
#915000
b11 E
b0 "
b0 +
b0 4
b0 G
b1 !
b1 *
b1 1
b0 )
b0 0
b0 2
b0 F
1#
#920000
0#
#925000
b11 "
b11 +
b11 4
b11 G
b10 E
b110 !
b110 *
b110 1
b11 )
b11 0
b11 2
b11 F
1#
#930000
0#
#935000
b10 "
b10 +
b10 4
b10 G
b1 E
b10010 !
b10010 *
b10010 1
b10 )
b10 0
b10 2
b10 F
1#
#940000
0#
#945000
b1 "
b1 +
b1 4
b1 G
b0 E
b1001111 !
b1001111 *
b1001111 1
b1 )
b1 0
b1 2
b1 F
1#
#950000
0#
#955000
b11 E
b0 "
b0 +
b0 4
b0 G
b1 !
b1 *
b1 1
b0 )
b0 0
b0 2
b0 F
1#
#960000
0#
#965000
b11 "
b11 +
b11 4
b11 G
b10 E
b110 !
b110 *
b110 1
b11 )
b11 0
b11 2
b11 F
1#
#970000
0#
#975000
b10 "
b10 +
b10 4
b10 G
b1 E
b10010 !
b10010 *
b10010 1
b10 )
b10 0
b10 2
b10 F
1#
#980000
0#
#985000
b1 "
b1 +
b1 4
b1 G
b0 E
b1001111 !
b1001111 *
b1001111 1
b1 )
b1 0
b1 2
b1 F
1#
#990000
0#
#995000
b11 E
b0 "
b0 +
b0 4
b0 G
b1 !
b1 *
b1 1
b0 )
b0 0
b0 2
b0 F
1#
#1000000
0#
#1005000
b11 "
b11 +
b11 4
b11 G
b10 E
b110 !
b110 *
b110 1
b11 )
b11 0
b11 2
b11 F
1#
#1010000
0#
#1015000
b10 "
b10 +
b10 4
b10 G
b1 E
b10010 !
b10010 *
b10010 1
b10 )
b10 0
b10 2
b10 F
1#
#1020000
0#
#1025000
b1 "
b1 +
b1 4
b1 G
b0 E
b1001111 !
b1001111 *
b1001111 1
b1 )
b1 0
b1 2
b1 F
1#
#1030000
0#
#1035000
b11 E
b0 "
b0 +
b0 4
b0 G
b1 !
b1 *
b1 1
b0 )
b0 0
b0 2
b0 F
1#
#1040000
0#
#1045000
b11 "
b11 +
b11 4
b11 G
b10 E
b110 !
b110 *
b110 1
b11 )
b11 0
b11 2
b11 F
1#
#1050000
0#
#1055000
b10 "
b10 +
b10 4
b10 G
b1 E
b10010 !
b10010 *
b10010 1
b10 )
b10 0
b10 2
b10 F
1#
#1060000
0#
#1065000
b1 "
b1 +
b1 4
b1 G
b0 E
b1001111 !
b1001111 *
b1001111 1
b1 )
b1 0
b1 2
b1 F
1#
#1070000
0#
#1075000
b11 E
b0 "
b0 +
b0 4
b0 G
b1 !
b1 *
b1 1
b0 )
b0 0
b0 2
b0 F
1#
#1080000
0#
#1085000
b11 "
b11 +
b11 4
b11 G
b10 E
b110 !
b110 *
b110 1
b11 )
b11 0
b11 2
b11 F
1#
#1090000
0#
#1095000
b10 "
b10 +
b10 4
b10 G
b1 E
b10010 !
b10010 *
b10010 1
b10 )
b10 0
b10 2
b10 F
1#
#1100000
0#
#1105000
b1 "
b1 +
b1 4
b1 G
b0 E
b1001111 !
b1001111 *
b1001111 1
b1 )
b1 0
b1 2
b1 F
1#
#1110000
0#
#1115000
b11 E
b0 "
b0 +
b0 4
b0 G
b1 !
b1 *
b1 1
b0 )
b0 0
b0 2
b0 F
1#
#1120000
0#
#1125000
b11 "
b11 +
b11 4
b11 G
b10 E
b110 !
b110 *
b110 1
b11 )
b11 0
b11 2
b11 F
1#
#1130000
0#
#1135000
b10 "
b10 +
b10 4
b10 G
b1 E
b10010 !
b10010 *
b10010 1
b10 )
b10 0
b10 2
b10 F
1#
#1140000
0#
#1145000
b1 "
b1 +
b1 4
b1 G
b0 E
b1001111 !
b1001111 *
b1001111 1
b1 )
b1 0
b1 2
b1 F
1#
#1150000
0#
#1155000
b11 E
b0 "
b0 +
b0 4
b0 G
b1 !
b1 *
b1 1
b0 )
b0 0
b0 2
b0 F
1#
#1160000
0#
#1165000
b11 "
b11 +
b11 4
b11 G
b10 E
b110 !
b110 *
b110 1
b11 )
b11 0
b11 2
b11 F
1#
#1170000
0#
#1175000
b10 "
b10 +
b10 4
b10 G
b1 E
b10010 !
b10010 *
b10010 1
b10 )
b10 0
b10 2
b10 F
1#
#1180000
0#
#1185000
b1 "
b1 +
b1 4
b1 G
b0 E
b1001111 !
b1001111 *
b1001111 1
b1 )
b1 0
b1 2
b1 F
1#
#1190000
0#
#1195000
b11 E
b0 "
b0 +
b0 4
b0 G
b1 !
b1 *
b1 1
b0 )
b0 0
b0 2
b0 F
1#
#1200000
b0 E
0#
b11 $
b11 (
b11 3
